{"NumMachines": 2, "Jobs": [{"Id": 0, "Operations": [{"Id": 0, "MachineIndex": 0, "ProcessingTime": 38, "PowerConsumption": 38.38159476331509}]}, {"Id": 1, "Operations": [{"Id": 1, "MachineIndex": 1, "ProcessingTime": 18, "PowerConsumption": 47.40862070927798}]}, {"Id": 2, "Operations": [{"Id": 2, "MachineIndex": 1, "ProcessingTime": 33, "PowerConsumption": 38.34910292101517}]}, {"Id": 3, "Operations": [{"Id": 3, "MachineIndex": 0, "ProcessingTime": 43, "PowerConsumption": 47.97920102625117}]}, {"Id": 4, "Operations": [{"Id": 4, "MachineIndex": 1, "ProcessingTime": 41, "PowerConsumption": 43.314525955347904}]}, {"Id": 5, "Operations": [{"Id": 5, "MachineIndex": 0, "ProcessingTime": 19, "PowerConsumption": 36.631137025526016}]}, {"Id": 6, "Operations": [{"Id": 6, "MachineIndex": 1, "ProcessingTime": 59, "PowerConsumption": 43.18647495308882}]}, {"Id": 7, "Operations": [{"Id": 7, "MachineIndex": 1, "ProcessingTime": 40, "PowerConsumption": 46.01762728424943}]}, {"Id": 8, "Operations": [{"Id": 8, "MachineIndex": 0, "ProcessingTime": 30, "PowerConsumption": 45.48795017358907}]}, {"Id": 9, "Operations": [{"Id": 9, "MachineIndex": 1, "ProcessingTime": 44, "PowerConsumption": 49.0315863780514}]}, {"Id": 10, "Operations": [{"Id": 10, "MachineIndex": 0, "ProcessingTime": 33, "PowerConsumption": 41.65170529934191}]}, {"Id": 11, "Operations": [{"Id": 11, "MachineIndex": 1, "ProcessingTime": 49, "PowerConsumption": 35.50016242180338}]}, {"Id": 12, "Operations": [{"Id": 12, "MachineIndex": 0, "ProcessingTime": 27, "PowerConsumption": 51.771803410617544}]}, {"Id": 13, "Operations": [{"Id": 13, "MachineIndex": 1, "ProcessingTime": 35, "PowerConsumption": 61.449136132428336}]}, {"Id": 14, "Operations": [{"Id": 14, "MachineIndex": 0, "ProcessingTime": 32, "PowerConsumption": 57.43246258116908}]}, {"Id": 15, "Operations": [{"Id": 15, "MachineIndex": 0, "ProcessingTime": 35, "PowerConsumption": 46.847380021050284}]}, {"Id": 16, "Operations": [{"Id": 16, "MachineIndex": 0, "ProcessingTime": 42, "PowerConsumption": 66.09542110597812}]}, {"Id": 17, "Operations": [{"Id": 17, "MachineIndex": 0, "ProcessingTime": 32, "PowerConsumption": 46.15032896996336}]}, {"Id": 18, "Operations": [{"Id": 18, "MachineIndex": 1, "ProcessingTime": 39, "PowerConsumption": 65.35699400058498}]}, {"Id": 19, "Operations": [{"Id": 19, "MachineIndex": 0, "ProcessingTime": 55, "PowerConsumption": 57.98483104040761}]}, {"Id": 20, "Operations": [{"Id": 20, "MachineIndex": 1, "ProcessingTime": 19, "PowerConsumption": 58.23827657145679}]}, {"Id": 21, "Operations": [{"Id": 21, "MachineIndex": 0, "ProcessingTime": 53, "PowerConsumption": 41.24517348032065}]}, {"Id": 22, "Operations": [{"Id": 22, "MachineIndex": 0, "ProcessingTime": 56, "PowerConsumption": 60.70303506871517}]}, {"Id": 23, "Operations": [{"Id": 23, "MachineIndex": 1, "ProcessingTime": 48, "PowerConsumption": 60.1621093508611}]}, {"Id": 24, "Operations": [{"Id": 24, "MachineIndex": 0, "ProcessingTime": 21, "PowerConsumption": 51.0373155979303}]}, {"Id": 25, "Operations": [{"Id": 25, "MachineIndex": 1, "ProcessingTime": 32, "PowerConsumption": 39.56550212556753}]}, {"Id": 26, "Operations": [{"Id": 26, "MachineIndex": 1, "ProcessingTime": 25, "PowerConsumption": 62.86888204648574}]}, {"Id": 27, "Operations": [{"Id": 27, "MachineIndex": 0, "ProcessingTime": 1, "PowerConsumption": 35.197037164368844}]}, {"Id": 28, "Operations": [{"Id": 28, "MachineIndex": 1, "ProcessingTime": 5, "PowerConsumption": 33.90590450753112}]}, {"Id": 29, "Operations": [{"Id": 29, "MachineIndex": 0, "ProcessingTime": 14, "PowerConsumption": 40.59833965292123}]}], "EnergyLimit": 1000.0, "Horizon": 1020, "LengthMeteringInterval": 15, "Metadata": {"spannableRatio": 0.9, "repetition": 6, "numMachines": 2, "numJobs": 30, "powerConsumptionLbMultiplier": 1.0}}