{"NumMachines": 2, "Jobs": [{"Id": 0, "Operations": [{"Id": 0, "MachineIndex": 0, "ProcessingTime": 30, "PowerConsumption": 47.23567868609401}]}, {"Id": 1, "Operations": [{"Id": 1, "MachineIndex": 1, "ProcessingTime": 47, "PowerConsumption": 53.48336101206176}]}, {"Id": 2, "Operations": [{"Id": 2, "MachineIndex": 0, "ProcessingTime": 25, "PowerConsumption": 60.96586712681031}]}, {"Id": 3, "Operations": [{"Id": 3, "MachineIndex": 1, "ProcessingTime": 53, "PowerConsumption": 43.267449663610876}]}, {"Id": 4, "Operations": [{"Id": 4, "MachineIndex": 1, "ProcessingTime": 19, "PowerConsumption": 59.073850546221806}]}, {"Id": 5, "Operations": [{"Id": 5, "MachineIndex": 0, "ProcessingTime": 18, "PowerConsumption": 58.15879241477642}]}, {"Id": 6, "Operations": [{"Id": 6, "MachineIndex": 1, "ProcessingTime": 34, "PowerConsumption": 59.59055376220055}]}, {"Id": 7, "Operations": [{"Id": 7, "MachineIndex": 0, "ProcessingTime": 10, "PowerConsumption": 51.091327784159844}]}, {"Id": 8, "Operations": [{"Id": 8, "MachineIndex": 1, "ProcessingTime": 1, "PowerConsumption": 48.31482150047776}]}, {"Id": 9, "Operations": [{"Id": 9, "MachineIndex": 0, "ProcessingTime": 4, "PowerConsumption": 44.256186636284085}]}, {"Id": 10, "Operations": [{"Id": 10, "MachineIndex": 0, "ProcessingTime": 2, "PowerConsumption": 65.8695924899244}]}, {"Id": 11, "Operations": [{"Id": 11, "MachineIndex": 0, "ProcessingTime": 7, "PowerConsumption": 65.49342459633951}]}, {"Id": 12, "Operations": [{"Id": 12, "MachineIndex": 1, "ProcessingTime": 14, "PowerConsumption": 59.58476482250329}]}, {"Id": 13, "Operations": [{"Id": 13, "MachineIndex": 1, "ProcessingTime": 9, "PowerConsumption": 52.94616056588144}]}, {"Id": 14, "Operations": [{"Id": 14, "MachineIndex": 0, "ProcessingTime": 4, "PowerConsumption": 56.73855556333681}]}, {"Id": 15, "Operations": [{"Id": 15, "MachineIndex": 1, "ProcessingTime": 12, "PowerConsumption": 43.26651311321177}]}, {"Id": 16, "Operations": [{"Id": 16, "MachineIndex": 1, "ProcessingTime": 6, "PowerConsumption": 52.390890537011856}]}, {"Id": 17, "Operations": [{"Id": 17, "MachineIndex": 1, "ProcessingTime": 4, "PowerConsumption": 55.66879291817024}]}, {"Id": 18, "Operations": [{"Id": 18, "MachineIndex": 1, "ProcessingTime": 8, "PowerConsumption": 57.821685046805854}]}, {"Id": 19, "Operations": [{"Id": 19, "MachineIndex": 0, "ProcessingTime": 10, "PowerConsumption": 59.30959806745388}]}, {"Id": 20, "Operations": [{"Id": 20, "MachineIndex": 1, "ProcessingTime": 4, "PowerConsumption": 65.58823327173242}]}, {"Id": 21, "Operations": [{"Id": 21, "MachineIndex": 0, "ProcessingTime": 11, "PowerConsumption": 60.29795682382054}]}, {"Id": 22, "Operations": [{"Id": 22, "MachineIndex": 1, "ProcessingTime": 8, "PowerConsumption": 56.8441847293533}]}, {"Id": 23, "Operations": [{"Id": 23, "MachineIndex": 1, "ProcessingTime": 13, "PowerConsumption": 43.57023383346552}]}, {"Id": 24, "Operations": [{"Id": 24, "MachineIndex": 0, "ProcessingTime": 12, "PowerConsumption": 61.54721557855632}]}, {"Id": 25, "Operations": [{"Id": 25, "MachineIndex": 1, "ProcessingTime": 11, "PowerConsumption": 50.301056931245945}]}, {"Id": 26, "Operations": [{"Id": 26, "MachineIndex": 0, "ProcessingTime": 1, "PowerConsumption": 45.43812380735986}]}, {"Id": 27, "Operations": [{"Id": 27, "MachineIndex": 1, "ProcessingTime": 12, "PowerConsumption": 62.70115156783776}]}, {"Id": 28, "Operations": [{"Id": 28, "MachineIndex": 0, "ProcessingTime": 10, "PowerConsumption": 61.4665076112374}]}, {"Id": 29, "Operations": [{"Id": 29, "MachineIndex": 0, "ProcessingTime": 5, "PowerConsumption": 64.29101637143535}]}], "EnergyLimit": 1000.0, "Horizon": 405, "LengthMeteringInterval": 15, "Metadata": {"spannableRatio": 0.25, "repetition": 6, "numMachines": 2, "numJobs": 30, "powerConsumptionLbMultiplier": 1.2}}