{"NumMachines": 2, "Jobs": [{"Id": 0, "Operations": [{"Id": 0, "MachineIndex": 1, "ProcessingTime": 17, "PowerConsumption": 64.02393328523758}]}, {"Id": 1, "Operations": [{"Id": 1, "MachineIndex": 1, "ProcessingTime": 41, "PowerConsumption": 65.90978705599429}]}, {"Id": 2, "Operations": [{"Id": 2, "MachineIndex": 0, "ProcessingTime": 51, "PowerConsumption": 60.08885029397076}]}, {"Id": 3, "Operations": [{"Id": 3, "MachineIndex": 1, "ProcessingTime": 18, "PowerConsumption": 57.97829287342958}]}, {"Id": 4, "Operations": [{"Id": 4, "MachineIndex": 1, "ProcessingTime": 40, "PowerConsumption": 61.04659385717471}]}, {"Id": 5, "Operations": [{"Id": 5, "MachineIndex": 0, "ProcessingTime": 28, "PowerConsumption": 63.90765058989993}]}, {"Id": 6, "Operations": [{"Id": 6, "MachineIndex": 1, "ProcessingTime": 23, "PowerConsumption": 66.0497989130128}]}, {"Id": 7, "Operations": [{"Id": 7, "MachineIndex": 1, "ProcessingTime": 14, "PowerConsumption": 61.206929029217115}]}, {"Id": 8, "Operations": [{"Id": 8, "MachineIndex": 1, "ProcessingTime": 13, "PowerConsumption": 61.65487180541031}]}, {"Id": 9, "Operations": [{"Id": 9, "MachineIndex": 0, "ProcessingTime": 12, "PowerConsumption": 65.15412268468837}]}], "EnergyLimit": 1000.0, "Horizon": 270, "LengthMeteringInterval": 15, "Metadata": {"spannableRatio": 0.75, "repetition": 4, "numMachines": 2, "numJobs": 10, "powerConsumptionLbMultiplier": 1.6}}