{"NumMachines": 2, "Jobs": [{"Id": 0, "Operations": [{"Id": 0, "MachineIndex": 1, "ProcessingTime": 17, "PowerConsumption": 57.559608837694995}]}, {"Id": 1, "Operations": [{"Id": 1, "MachineIndex": 0, "ProcessingTime": 47, "PowerConsumption": 56.486284659781006}]}, {"Id": 2, "Operations": [{"Id": 2, "MachineIndex": 1, "ProcessingTime": 57, "PowerConsumption": 36.022781404987654}]}, {"Id": 3, "Operations": [{"Id": 3, "MachineIndex": 0, "ProcessingTime": 38, "PowerConsumption": 31.10020222969673}]}, {"Id": 4, "Operations": [{"Id": 4, "MachineIndex": 0, "ProcessingTime": 54, "PowerConsumption": 41.27891282920986}]}, {"Id": 5, "Operations": [{"Id": 5, "MachineIndex": 0, "ProcessingTime": 10, "PowerConsumption": 35.218067272512585}]}, {"Id": 6, "Operations": [{"Id": 6, "MachineIndex": 1, "ProcessingTime": 10, "PowerConsumption": 32.88306989686086}]}, {"Id": 7, "Operations": [{"Id": 7, "MachineIndex": 1, "ProcessingTime": 10, "PowerConsumption": 51.37318709773936}]}, {"Id": 8, "Operations": [{"Id": 8, "MachineIndex": 0, "ProcessingTime": 2, "PowerConsumption": 54.63885126696225}]}, {"Id": 9, "Operations": [{"Id": 9, "MachineIndex": 0, "ProcessingTime": 6, "PowerConsumption": 60.651593137215016}]}], "EnergyLimit": 1000.0, "Horizon": 255, "LengthMeteringInterval": 15, "Metadata": {"spannableRatio": 0.5, "repetition": 5, "numMachines": 2, "numJobs": 10, "powerConsumptionLbMultiplier": 0.8}}