{"NumMachines": 4, "Jobs": [{"Id": 0, "Operations": [{"Id": 0, "MachineIndex": 2, "ProcessingTime": 56, "PowerConsumption": 14.414997327955595}]}, {"Id": 1, "Operations": [{"Id": 1, "MachineIndex": 0, "ProcessingTime": 4, "PowerConsumption": 31.57590440703055}]}, {"Id": 2, "Operations": [{"Id": 2, "MachineIndex": 1, "ProcessingTime": 6, "PowerConsumption": 13.578610116109227}]}, {"Id": 3, "Operations": [{"Id": 3, "MachineIndex": 3, "ProcessingTime": 9, "PowerConsumption": 27.504724534618695}]}, {"Id": 4, "Operations": [{"Id": 4, "MachineIndex": 2, "ProcessingTime": 6, "PowerConsumption": 23.28925738885188}]}, {"Id": 5, "Operations": [{"Id": 5, "MachineIndex": 2, "ProcessingTime": 1, "PowerConsumption": 30.148221479487397}]}, {"Id": 6, "Operations": [{"Id": 6, "MachineIndex": 2, "ProcessingTime": 7, "PowerConsumption": 22.779759464838122}]}, {"Id": 7, "Operations": [{"Id": 7, "MachineIndex": 1, "ProcessingTime": 13, "PowerConsumption": 30.988742171005384}]}, {"Id": 8, "Operations": [{"Id": 8, "MachineIndex": 3, "ProcessingTime": 2, "PowerConsumption": 23.54483442235653}]}, {"Id": 9, "Operations": [{"Id": 9, "MachineIndex": 1, "ProcessingTime": 10, "PowerConsumption": 32.13140651838143}]}], "EnergyLimit": 1000.0, "Horizon": 120, "LengthMeteringInterval": 15, "Metadata": {"spannableRatio": 0.1, "repetition": 5, "numMachines": 4, "numJobs": 10, "powerConsumptionLbMultiplier": 0.8}}