{"NumMachines": 4, "Jobs": [{"Id": 0, "Operations": [{"Id": 0, "MachineIndex": 3, "ProcessingTime": 49, "PowerConsumption": 20.754299785051323}]}, {"Id": 1, "Operations": [{"Id": 1, "MachineIndex": 0, "ProcessingTime": 53, "PowerConsumption": 26.36428144746349}]}, {"Id": 2, "Operations": [{"Id": 2, "MachineIndex": 2, "ProcessingTime": 4, "PowerConsumption": 21.16089740201252}]}, {"Id": 3, "Operations": [{"Id": 3, "MachineIndex": 3, "ProcessingTime": 12, "PowerConsumption": 29.06078776145701}]}, {"Id": 4, "Operations": [{"Id": 4, "MachineIndex": 3, "ProcessingTime": 8, "PowerConsumption": 20.09938163687446}]}, {"Id": 5, "Operations": [{"Id": 5, "MachineIndex": 1, "ProcessingTime": 5, "PowerConsumption": 26.05694640088995}]}, {"Id": 6, "Operations": [{"Id": 6, "MachineIndex": 3, "ProcessingTime": 10, "PowerConsumption": 29.483506050651663}]}, {"Id": 7, "Operations": [{"Id": 7, "MachineIndex": 0, "ProcessingTime": 13, "PowerConsumption": 27.557109945557908}]}, {"Id": 8, "Operations": [{"Id": 8, "MachineIndex": 3, "ProcessingTime": 1, "PowerConsumption": 26.021947503410566}]}, {"Id": 9, "Operations": [{"Id": 9, "MachineIndex": 3, "ProcessingTime": 1, "PowerConsumption": 29.42331885116019}]}], "EnergyLimit": 1000.0, "Horizon": 165, "LengthMeteringInterval": 15, "Metadata": {"spannableRatio": 0.25, "repetition": 8, "numMachines": 4, "numJobs": 10, "powerConsumptionLbMultiplier": 1.2}}