{"NumMachines": 4, "Jobs": [{"Id": 0, "Operations": [{"Id": 0, "MachineIndex": 1, "ProcessingTime": 39, "PowerConsumption": 32.35115624763281}]}, {"Id": 1, "Operations": [{"Id": 1, "MachineIndex": 2, "ProcessingTime": 12, "PowerConsumption": 32.59035819020295}]}, {"Id": 2, "Operations": [{"Id": 2, "MachineIndex": 0, "ProcessingTime": 3, "PowerConsumption": 28.009478361971123}]}, {"Id": 3, "Operations": [{"Id": 3, "MachineIndex": 3, "ProcessingTime": 12, "PowerConsumption": 23.555422880169356}]}, {"Id": 4, "Operations": [{"Id": 4, "MachineIndex": 2, "ProcessingTime": 4, "PowerConsumption": 27.374766827890696}]}, {"Id": 5, "Operations": [{"Id": 5, "MachineIndex": 2, "ProcessingTime": 2, "PowerConsumption": 32.98554660581}]}, {"Id": 6, "Operations": [{"Id": 6, "MachineIndex": 0, "ProcessingTime": 8, "PowerConsumption": 26.381041570433588}]}, {"Id": 7, "Operations": [{"Id": 7, "MachineIndex": 3, "ProcessingTime": 8, "PowerConsumption": 25.352305252424273}]}, {"Id": 8, "Operations": [{"Id": 8, "MachineIndex": 0, "ProcessingTime": 10, "PowerConsumption": 23.543364925718258}]}, {"Id": 9, "Operations": [{"Id": 9, "MachineIndex": 0, "ProcessingTime": 3, "PowerConsumption": 32.264078778958606}]}], "EnergyLimit": 1000.0, "Horizon": 105, "LengthMeteringInterval": 15, "Metadata": {"spannableRatio": 0.1, "repetition": 5, "numMachines": 4, "numJobs": 10, "powerConsumptionLbMultiplier": 1.4}}