{"NumMachines": 2, "Jobs": [{"Id": 0, "Operations": [{"Id": 0, "MachineIndex": 0, "ProcessingTime": 45, "PowerConsumption": 62.00206580044177}]}, {"Id": 1, "Operations": [{"Id": 1, "MachineIndex": 0, "ProcessingTime": 21, "PowerConsumption": 43.42838057786927}]}, {"Id": 2, "Operations": [{"Id": 2, "MachineIndex": 1, "ProcessingTime": 57, "PowerConsumption": 52.12701031882022}]}, {"Id": 3, "Operations": [{"Id": 3, "MachineIndex": 0, "ProcessingTime": 31, "PowerConsumption": 58.38358249129584}]}, {"Id": 4, "Operations": [{"Id": 4, "MachineIndex": 1, "ProcessingTime": 33, "PowerConsumption": 66.48862862330333}]}, {"Id": 5, "Operations": [{"Id": 5, "MachineIndex": 1, "ProcessingTime": 26, "PowerConsumption": 63.51772960128778}]}, {"Id": 6, "Operations": [{"Id": 6, "MachineIndex": 1, "ProcessingTime": 28, "PowerConsumption": 45.96263579060136}]}, {"Id": 7, "Operations": [{"Id": 7, "MachineIndex": 1, "ProcessingTime": 32, "PowerConsumption": 65.72519866084923}]}, {"Id": 8, "Operations": [{"Id": 8, "MachineIndex": 0, "ProcessingTime": 53, "PowerConsumption": 47.8376229268053}]}, {"Id": 9, "Operations": [{"Id": 9, "MachineIndex": 0, "ProcessingTime": 30, "PowerConsumption": 40.33645787602436}]}, {"Id": 10, "Operations": [{"Id": 10, "MachineIndex": 0, "ProcessingTime": 6, "PowerConsumption": 57.163028874044784}]}, {"Id": 11, "Operations": [{"Id": 11, "MachineIndex": 0, "ProcessingTime": 10, "PowerConsumption": 51.136201414187845}]}, {"Id": 12, "Operations": [{"Id": 12, "MachineIndex": 0, "ProcessingTime": 9, "PowerConsumption": 43.052594377528536}]}, {"Id": 13, "Operations": [{"Id": 13, "MachineIndex": 0, "ProcessingTime": 11, "PowerConsumption": 42.782775624398816}]}, {"Id": 14, "Operations": [{"Id": 14, "MachineIndex": 0, "ProcessingTime": 6, "PowerConsumption": 63.460431519644544}]}, {"Id": 15, "Operations": [{"Id": 15, "MachineIndex": 1, "ProcessingTime": 10, "PowerConsumption": 45.21730934823117}]}, {"Id": 16, "Operations": [{"Id": 16, "MachineIndex": 0, "ProcessingTime": 6, "PowerConsumption": 42.501796534829055}]}, {"Id": 17, "Operations": [{"Id": 17, "MachineIndex": 0, "ProcessingTime": 9, "PowerConsumption": 42.81367148093274}]}, {"Id": 18, "Operations": [{"Id": 18, "MachineIndex": 1, "ProcessingTime": 5, "PowerConsumption": 47.90045697609916}]}, {"Id": 19, "Operations": [{"Id": 19, "MachineIndex": 1, "ProcessingTime": 10, "PowerConsumption": 47.27210150749365}]}], "EnergyLimit": 1000.0, "Horizon": 450, "LengthMeteringInterval": 15, "Metadata": {"spannableRatio": 0.5, "repetition": 3, "numMachines": 2, "numJobs": 20, "powerConsumptionLbMultiplier": 1.2}}