{"NumMachines": 4, "Jobs": [{"Id": 0, "Operations": [{"Id": 0, "MachineIndex": 0, "ProcessingTime": 40, "PowerConsumption": 18.95390614508057}]}, {"Id": 1, "Operations": [{"Id": 1, "MachineIndex": 2, "ProcessingTime": 16, "PowerConsumption": 17.484008646950752}]}, {"Id": 2, "Operations": [{"Id": 2, "MachineIndex": 2, "ProcessingTime": 46, "PowerConsumption": 18.763451973021397}]}, {"Id": 3, "Operations": [{"Id": 3, "MachineIndex": 3, "ProcessingTime": 57, "PowerConsumption": 24.309150296096917}]}, {"Id": 4, "Operations": [{"Id": 4, "MachineIndex": 2, "ProcessingTime": 43, "PowerConsumption": 32.960822398911304}]}, {"Id": 5, "Operations": [{"Id": 5, "MachineIndex": 2, "ProcessingTime": 30, "PowerConsumption": 18.489556690595528}]}, {"Id": 6, "Operations": [{"Id": 6, "MachineIndex": 0, "ProcessingTime": 43, "PowerConsumption": 33.035405839965094}]}, {"Id": 7, "Operations": [{"Id": 7, "MachineIndex": 2, "ProcessingTime": 53, "PowerConsumption": 31.301667338532866}]}, {"Id": 8, "Operations": [{"Id": 8, "MachineIndex": 3, "ProcessingTime": 21, "PowerConsumption": 24.585563921331847}]}, {"Id": 9, "Operations": [{"Id": 9, "MachineIndex": 3, "ProcessingTime": 39, "PowerConsumption": 28.756154264365087}]}, {"Id": 10, "Operations": [{"Id": 10, "MachineIndex": 2, "ProcessingTime": 11, "PowerConsumption": 23.160308271876367}]}, {"Id": 11, "Operations": [{"Id": 11, "MachineIndex": 0, "ProcessingTime": 7, "PowerConsumption": 20.802543616916928}]}, {"Id": 12, "Operations": [{"Id": 12, "MachineIndex": 0, "ProcessingTime": 10, "PowerConsumption": 31.952003652828438}]}, {"Id": 13, "Operations": [{"Id": 13, "MachineIndex": 0, "ProcessingTime": 9, "PowerConsumption": 19.653571561438454}]}, {"Id": 14, "Operations": [{"Id": 14, "MachineIndex": 2, "ProcessingTime": 3, "PowerConsumption": 24.104344005434626}]}, {"Id": 15, "Operations": [{"Id": 15, "MachineIndex": 3, "ProcessingTime": 2, "PowerConsumption": 17.698161839987847}]}, {"Id": 16, "Operations": [{"Id": 16, "MachineIndex": 1, "ProcessingTime": 5, "PowerConsumption": 32.97433833885364}]}, {"Id": 17, "Operations": [{"Id": 17, "MachineIndex": 3, "ProcessingTime": 14, "PowerConsumption": 25.7165590017335}]}, {"Id": 18, "Operations": [{"Id": 18, "MachineIndex": 1, "ProcessingTime": 3, "PowerConsumption": 27.378327474329463}]}, {"Id": 19, "Operations": [{"Id": 19, "MachineIndex": 2, "ProcessingTime": 9, "PowerConsumption": 30.970830286063332}]}], "EnergyLimit": 1000.0, "Horizon": 465, "LengthMeteringInterval": 15, "Metadata": {"spannableRatio": 0.5, "repetition": 3, "numMachines": 4, "numJobs": 20, "powerConsumptionLbMultiplier": 0.8}}