{"NumMachines": 4, "Jobs": [{"Id": 0, "Operations": [{"Id": 0, "MachineIndex": 2, "ProcessingTime": 22, "PowerConsumption": 21.626012673737797}]}, {"Id": 1, "Operations": [{"Id": 1, "MachineIndex": 1, "ProcessingTime": 17, "PowerConsumption": 30.58196175094475}]}, {"Id": 2, "Operations": [{"Id": 2, "MachineIndex": 1, "ProcessingTime": 50, "PowerConsumption": 28.913229645965576}]}, {"Id": 3, "Operations": [{"Id": 3, "MachineIndex": 2, "ProcessingTime": 38, "PowerConsumption": 27.634482225853866}]}, {"Id": 4, "Operations": [{"Id": 4, "MachineIndex": 3, "ProcessingTime": 33, "PowerConsumption": 31.401638089710993}]}, {"Id": 5, "Operations": [{"Id": 5, "MachineIndex": 2, "ProcessingTime": 54, "PowerConsumption": 21.392452736102257}]}, {"Id": 6, "Operations": [{"Id": 6, "MachineIndex": 3, "ProcessingTime": 48, "PowerConsumption": 31.71017113376572}]}, {"Id": 7, "Operations": [{"Id": 7, "MachineIndex": 0, "ProcessingTime": 21, "PowerConsumption": 27.43158048364873}]}, {"Id": 8, "Operations": [{"Id": 8, "MachineIndex": 0, "ProcessingTime": 41, "PowerConsumption": 32.628950755715195}]}, {"Id": 9, "Operations": [{"Id": 9, "MachineIndex": 1, "ProcessingTime": 52, "PowerConsumption": 27.823118558692027}]}, {"Id": 10, "Operations": [{"Id": 10, "MachineIndex": 0, "ProcessingTime": 57, "PowerConsumption": 23.35512489857546}]}, {"Id": 11, "Operations": [{"Id": 11, "MachineIndex": 0, "ProcessingTime": 27, "PowerConsumption": 31.176258461166295}]}, {"Id": 12, "Operations": [{"Id": 12, "MachineIndex": 3, "ProcessingTime": 46, "PowerConsumption": 21.694625523730473}]}, {"Id": 13, "Operations": [{"Id": 13, "MachineIndex": 2, "ProcessingTime": 29, "PowerConsumption": 24.25316665519642}]}, {"Id": 14, "Operations": [{"Id": 14, "MachineIndex": 1, "ProcessingTime": 31, "PowerConsumption": 29.611789923911818}]}, {"Id": 15, "Operations": [{"Id": 15, "MachineIndex": 1, "ProcessingTime": 32, "PowerConsumption": 31.48336051566683}]}, {"Id": 16, "Operations": [{"Id": 16, "MachineIndex": 1, "ProcessingTime": 42, "PowerConsumption": 29.00162596674712}]}, {"Id": 17, "Operations": [{"Id": 17, "MachineIndex": 3, "ProcessingTime": 59, "PowerConsumption": 29.767449136404686}]}, {"Id": 18, "Operations": [{"Id": 18, "MachineIndex": 2, "ProcessingTime": 6, "PowerConsumption": 20.237166192493014}]}, {"Id": 19, "Operations": [{"Id": 19, "MachineIndex": 3, "ProcessingTime": 9, "PowerConsumption": 26.101013909141074}]}], "EnergyLimit": 1000.0, "Horizon": 720, "LengthMeteringInterval": 15, "Metadata": {"spannableRatio": 0.9, "repetition": 9, "numMachines": 4, "numJobs": 20, "powerConsumptionLbMultiplier": 1.2}}