{"NumMachines": 2, "Jobs": [{"Id": 0, "Operations": [{"Id": 0, "MachineIndex": 0, "ProcessingTime": 32, "PowerConsumption": 36.20593358585887}]}, {"Id": 1, "Operations": [{"Id": 1, "MachineIndex": 1, "ProcessingTime": 13, "PowerConsumption": 59.29054709118351}]}, {"Id": 2, "Operations": [{"Id": 2, "MachineIndex": 1, "ProcessingTime": 12, "PowerConsumption": 63.39906570349467}]}, {"Id": 3, "Operations": [{"Id": 3, "MachineIndex": 1, "ProcessingTime": 6, "PowerConsumption": 58.21649945568441}]}, {"Id": 4, "Operations": [{"Id": 4, "MachineIndex": 0, "ProcessingTime": 9, "PowerConsumption": 47.360466644490984}]}, {"Id": 5, "Operations": [{"Id": 5, "MachineIndex": 1, "ProcessingTime": 11, "PowerConsumption": 60.21712816330471}]}, {"Id": 6, "Operations": [{"Id": 6, "MachineIndex": 0, "ProcessingTime": 8, "PowerConsumption": 47.678782595792846}]}, {"Id": 7, "Operations": [{"Id": 7, "MachineIndex": 1, "ProcessingTime": 9, "PowerConsumption": 53.07585813713999}]}, {"Id": 8, "Operations": [{"Id": 8, "MachineIndex": 0, "ProcessingTime": 3, "PowerConsumption": 42.594479152899154}]}, {"Id": 9, "Operations": [{"Id": 9, "MachineIndex": 0, "ProcessingTime": 1, "PowerConsumption": 64.25866695629682}]}], "EnergyLimit": 1000.0, "Horizon": 105, "LengthMeteringInterval": 15, "Metadata": {"spannableRatio": 0.1, "repetition": 9, "numMachines": 2, "numJobs": 10, "powerConsumptionLbMultiplier": 1.0}}